ome_metadata-0.4.0.dist-info/METADATA
ome_metadata-0.4.0.dist-info/WHEEL
ome_metadata-0.4.0.dist-info/licenses/LICENSE
ome_metadata/__init__.py
ome_metadata/ome_metadata_rs.abi3.so
ome_metadata-0.4.0.dist-info/RECORD
