Metadata-Version: 2.4
Name: ome-metadata
Version: 0.4.0
Classifier: License :: OSI Approved :: MIT License
Classifier: Programming Language :: Rust
Classifier: Programming Language :: Python
Classifier: Programming Language :: Python :: 3
Classifier: Programming Language :: Python :: 3 :: Only
Classifier: Programming Language :: Python :: 3.10
Classifier: Programming Language :: Python :: 3.11
Classifier: Programming Language :: Python :: 3.12
Classifier: Programming Language :: Python :: 3.13
Classifier: Programming Language :: Python :: 3.14
License-File: LICENSE
Summary: Ome metadata as a rust/python structure.
Keywords: bioformats,imread,ome,metadata
Home-Page: https://github.com/wimpomp/ome-metadata
Author: Wim Pomp <w.pomp@nki.nl>
Author-email: Wim Pomp <w.pomp@nki.nl>
License: MIT
Requires-Python: >=3.10
Project-URL: Repository, https://github.com/wimpomp/ome-metadata
